[
  {
    "id": 1,
    "id_pasien": 1,
    "tanggal": "2025-01-01",
    "jawaban_1": 3,
    "jawaban_2": 4,
    "jawaban_3": 3,
    "jawaban_4": 2,
    "jawaban_5": 4,
    "total_raw": 16,
    "total_percentage": 64,
    "kategori": "kuning"
  },
  {
    "id": 2,
    "id_pasien": 1,
    "tanggal": "2025-01-02",
    "jawaban_1": 4,
    "jawaban_2": 4,
    "jawaban_3": 3,
    "jawaban_4": 3,
    "jawaban_5": 4,
    "total_raw": 18,
    "total_percentage": 72,
    "kategori": "hijau"
  },
  {
    "id": 3,
    "id_pasien": 1,
    "tanggal": "2025-11-12",
    "jawaban_1": 1,
    "jawaban_2": 2,
    "jawaban_3": 5,
    "jawaban_4": 5,
    "jawaban_5": 5,
    "total_raw": 18,
    "total_percentage": 72,
    "kategori": "hijau"
  },
  {
    "id": 4,
    "id_pasien": 1,
    "tanggal": "2025-11-12",
    "jawaban_1": 5,
    "jawaban_2": 5,
    "jawaban_3": 5,
    "jawaban_4": 5,
    "jawaban_5": 5,
    "total_raw": 25,
    "total_percentage": 100,
    "kategori": "hijau"
  },
  {
    "id": 5,
    "id_pasien": 1,
    "tanggal": "2025-11-22",
    "jawaban_1": 1,
    "jawaban_2": 2,
    "jawaban_3": 5,
    "jawaban_4": 2,
    "jawaban_5": 2,
    "total_raw": 12,
    "total_percentage": 48,
    "kategori": "orange"
  },
  {
    "id": 5,
    "id_pasien": 1,
    "tanggal": "2025-11-22",
    "jawaban_1": 1,
    "jawaban_2": 2,
    "jawaban_3": 5,
    "jawaban_4": 2,
    "jawaban_5": 2,
    "total_raw": 12,
    "total_percentage": 48,
    "kategori": "orange"
  },
  {
    "id": 5,
    "id_pasien": 1,
    "tanggal": "2025-11-22",
    "jawaban_1": 1,
    "jawaban_2": 2,
    "jawaban_3": 5,
    "jawaban_4": 2,
    "jawaban_5": 2,
    "total_raw": 12,
    "total_percentage": 48,
    "kategori": "orange"
  },
  {
    "id": 5,
    "id_pasien": 1,
    "tanggal": "2025-11-22",
    "jawaban_1": 1,
    "jawaban_2": 2,
    "jawaban_3": 5,
    "jawaban_4": 2,
    "jawaban_5": 2,
    "total_raw": 12,
    "total_percentage": 48,
    "kategori": "orange"
  },
  {
    "id": 5,
    "id_pasien": 1,
    "tanggal": "2025-11-22",
    "jawaban_1": 1,
    "jawaban_2": 2,
    "jawaban_3": 5,
    "jawaban_4": 2,
    "jawaban_5": 2,
    "total_raw": 12,
    "total_percentage": 48,
    "kategori": "orange"
  },
  {
    "id": 5,
    "id_pasien": 1,
    "tanggal": "2025-11-22",
    "jawaban_1": 1,
    "jawaban_2": 2,
    "jawaban_3": 5,
    "jawaban_4": 2,
    "jawaban_5": 2,
    "total_raw": 12,
    "total_percentage": 48,
    "kategori": "orange"
  },
  {
    "id": 5,
    "id_pasien": 1,
    "tanggal": "2025-11-22",
    "jawaban_1": 1,
    "jawaban_2": 2,
    "jawaban_3": 5,
    "jawaban_4": 2,
    "jawaban_5": 2,
    "total_raw": 12,
    "total_percentage": 48,
    "kategori": "orange"
  },
  {
    "id": 5,
    "id_pasien": 1,
    "tanggal": "2025-11-22",
    "jawaban_1": 1,
    "jawaban_2": 2,
    "jawaban_3": 5,
    "jawaban_4": 2,
    "jawaban_5": 2,
    "total_raw": 12,
    "total_percentage": 48,
    "kategori": "orange"
  },
  {
    "id": 5,
    "id_pasien": 1,
    "tanggal": "2025-11-22",
    "jawaban_1": 1,
    "jawaban_2": 2,
    "jawaban_3": 5,
    "jawaban_4": 2,
    "jawaban_5": 2,
    "total_raw": 12,
    "total_percentage": 48,
    "kategori": "orange"
  },
  {
    "id": 5,
    "id_pasien": 1,
    "tanggal": "2025-11-22",
    "jawaban_1": 1,
    "jawaban_2": 2,
    "jawaban_3": 5,
    "jawaban_4": 2,
    "jawaban_5": 2,
    "total_raw": 12,
    "total_percentage": 48,
    "kategori": "orange"
  },
  {
    "id": 6,
    "id_pasien": 1,
    "tanggal": "2025-11-25",
    "jawaban_1": 2,
    "jawaban_2": 3,
    "jawaban_3": 4,
    "jawaban_4": 5,
    "jawaban_5": 0,
    "total_raw": 14,
    "total_percentage": 56,
    "kategori": "kuning"
  }
]